HexHue/HexHue.py
HexHue/__init__.py
HexHue-0.0.2.dist-info/METADATA
HexHue-0.0.2.dist-info/WHEEL
HexHue-0.0.2.dist-info/top_level.txt
HexHue-0.0.2.dist-info/RECORD
