Metadata-Version: 2.1
Name: HexHue
Version: 0.0.2
Summary: A simple Windows Terminal ANSI Escape Code Package
Author: aftxrlifx
Requires-Python: >=3.7
